LICENSE
MANIFEST.in
README.md
setup.py
imapbackup3/__init__.py
imapbackup3/cli.py
imapbackup3/imapbackup.py
imapbackup3.egg-info/PKG-INFO
imapbackup3.egg-info/SOURCES.txt
imapbackup3.egg-info/dependency_links.txt
imapbackup3.egg-info/entry_points.txt
imapbackup3.egg-info/top_level.txt