Metadata-Version: 2.1
Name: imapbackup3
Version: 0.2
Summary: UNKNOWN
Home-page: https://github.com/DavidMStraub/imapbackup3
Author: David M. Straub <straub@pm.me>
Author-email: straub@pm.me
License: MIT
Platform: UNKNOWN
